README.md
setup.cfg
setup.py
PyPNS/__init__.py
PyPNS/analyticFnGen.py
PyPNS/axonClass.py
PyPNS/bundleClass.py
PyPNS/constants.py
PyPNS/createGeometry.py
PyPNS/excitationMechanismClass.py
PyPNS/extracellularBackend.py
PyPNS/extracellularMechanismClass.py
PyPNS/generateAndSaveFieldDictFn.py
PyPNS/nameSetters.py
PyPNS/plotBundleClass.py
PyPNS/recordingMechanismClass.py
PyPNS/samplingRates.py
PyPNS/signalGeneration.py
PyPNS/silencer.py
PyPNS/spikeTrainGeneration.py
PyPNS/stimulusClass.py
PyPNS/takeTime.py
PyPNS/transmissionFunctions.py
PyPNS/upstreamSpikingClass.py
PyPNS.egg-info/PKG-INFO
PyPNS.egg-info/SOURCES.txt
PyPNS.egg-info/dependency_links.txt
PyPNS.egg-info/requires.txt
PyPNS.egg-info/top_level.txt