Metadata-Version: 1.2
Name: PyPNS
Version: 0.0.4
Summary: A peripheral nerve simulator built on NEURON
Home-page: https://github.com/caaarl/PyPNS
Maintainer: Carl H Lubba
Maintainer-email: c.lubba15@imperial.ac.uk
License: LICENSE
Download-URL: https://github.com/caaarl/PyPNS/archive/0.0.4.tar.gz
Platform: UNKNOWN
Provides: PyPNS
